yaroc-0.1.16.dist-info/METADATA
yaroc-0.1.16.dist-info/WHEEL
yaroc-0.1.16.dist-info/entry_points.txt
yaroc-0.1.16.dist-info/licenses/../LICENSE
yaroc/__init__.py
yaroc/clients/__init__.py
yaroc/clients/client.py
yaroc/clients/mop.py
yaroc/clients/mqtt.py
yaroc/clients/roc.py
yaroc/clients/sirap.py
yaroc/pb/coords_pb2.pyi
yaroc/pb/punches_pb2.py
yaroc/pb/punches_pb2.pyi
yaroc/pb/status_pb2.py
yaroc/pb/status_pb2.pyi
yaroc/pb/timestamp_pb2.py
yaroc/pb/timestamp_pb2.pyi
yaroc/pb/utils.py
yaroc/py.typed
yaroc/rs.abi3.so
yaroc/rs.pyi
yaroc/scripts/send_punch.py
yaroc/scripts/yarocd.py
yaroc/sources/meshtastic.py
yaroc/sources/si.py
yaroc/utils/__init__.py
yaroc/utils/async_serial.py
yaroc/utils/container.py
yaroc/utils/modem_manager.py
yaroc/utils/retries.py
yaroc/utils/sim7020.py
yaroc/utils/status.py
yaroc/utils/sys_info.py
yaroc-0.1.16.dist-info/RECORD
