Metadata-Version: 2.4
Name: yaroc
Version: 0.1.16
Classifier: Development Status :: 3 - Alpha
Classifier: Programming Language :: Python :: 3.11
Classifier: Programming Language :: Python :: 3.12
Classifier: Programming Language :: Python :: 3.13
Classifier: Programming Language :: Python :: 3 :: Only
Classifier: Programming Language :: Rust
Classifier: Programming Language :: Python :: Implementation :: CPython
Classifier: Programming Language :: Python :: Implementation :: PyPy
Requires-Dist: aiohttp-retry==2.9.1
Requires-Dist: aiohttp==3.12.*
Requires-Dist: aiomqtt==2.4.*
Requires-Dist: dbus-next==0.2.* ; platform_system == 'Linux'
Requires-Dist: dependency-injector==4.48.*
Requires-Dist: gpiozero==2.0.*
Requires-Dist: pillow==11.3.*
Requires-Dist: protobuf==5.29.*
Requires-Dist: psutil==7.1.*
Requires-Dist: pyserial-asyncio==0.6
Requires-Dist: rpi-gpio==0.7.1 ; (platform_machine == 'aarch64' and platform_system == 'Linux') or (platform_machine == 'armv6l' and platform_system == 'Linux') or (platform_machine == 'armv7l' and platform_system == 'Linux')
Requires-Dist: usb-monitor>=1.17
Requires-Dist: waveshare-epaper==1.2.0 ; platform_machine == 'aarch64' or platform_machine == 'armv7l'
Requires-Dist: ruff ; extra == 'dev'
Requires-Dist: mypy ; extra == 'dev'
Requires-Dist: pytest ; extra == 'dev'
Requires-Dist: types-pillow ; extra == 'dev'
Requires-Dist: types-protobuf ; extra == 'dev'
Requires-Dist: types-psutil ; extra == 'dev'
Requires-Dist: ruff-lsp ; extra == 'lsp'
Requires-Dist: pylsp-mypy ; extra == 'lsp'
Provides-Extra: dev
Provides-Extra: lsp
License-File: ../LICENSE
Summary: Yet Another ROC, radio online control
Keywords: sport,orienteering,split times,online control,radio control
Author-email: Lukáš Poláček <lukas@polacek.email>
Requires-Python: >=3.11
